ailess/.DS_Store
ailess/__init__.py
ailess/__main__.py
ailess/ailess.py
ailess/cli.py
ailess/modules/aws_utils.py
ailess/modules/cli_utils.py
ailess/modules/config_utils.py
ailess/modules/docker_utils.py
ailess/modules/python_utils.py
ailess/modules/terraform_utils.py
ailess/modules/docker_searchers/__init__.py
ailess/modules/docker_searchers/python_basic.py
ailess/modules/docker_searchers/pytorch_amd64_nvidia.py
ailess/modules/docker_searchers/tensorflow_amd64_nvidia.py
ailess/modules/terraform/cluster.tf
ailess/modules/terraform/iam_policy.json
ailess-0.1.3.dist-info/LICENSE
ailess-0.1.3.dist-info/METADATA
ailess-0.1.3.dist-info/WHEEL
ailess-0.1.3.dist-info/entry_points.txt
ailess-0.1.3.dist-info/top_level.txt
ailess-0.1.3.dist-info/RECORD
