Metadata-Version: 2.1
Name: ailess
Version: 0.1.3
License: MIT
License-File: LICENSE
Requires-Dist: typer >=0.9.0
Requires-Dist: inquirer >=3.1.3
Requires-Dist: boto3 >=1.26.146
Requires-Dist: yaspin >=2.3.0
Requires-Dist: pipreqs >=0.4.13
